async_cloud_tasks/__init__.py
async_cloud_tasks/apps.py
async_cloud_tasks/base.py
async_cloud_tasks/connection.py
async_cloud_tasks/constants.py
async_cloud_tasks/decorators.py
async_cloud_tasks/encoders.py
async_cloud_tasks/local.py
async_cloud_tasks/registries.py
async_cloud_tasks/urls.py
async_cloud_tasks/views.py
async_cloud_tasks-0.0.3.dist-info/LICENSE
async_cloud_tasks-0.0.3.dist-info/METADATA
async_cloud_tasks-0.0.3.dist-info/WHEEL
async_cloud_tasks-0.0.3.dist-info/top_level.txt
async_cloud_tasks-0.0.3.dist-info/RECORD
