Metadata-Version: 2.1
Name: async-cloud-tasks
Version: 0.0.3
Summary: Use Cloud Tasks to easily defer functions executions
Author-email: Everton Castro <evertoncastro.sp@gmail.com>
License: The MIT License        
Project-URL: Homepage, https://github.com/evertoncastro/async-cloud-tasks
Keywords: cloudtasks,cloud,tasks,async,defer
Classifier: License :: OSI Approved :: MIT License
Classifier: Programming Language :: Python
Classifier: Programming Language :: Python :: 3
Classifier: Programming Language :: Python :: 3.7
Requires-Python: >=3.7
License-File: LICENSE
Requires-Dist: google-cloud-tasks (>=2.9.0)
Provides-Extra: dev
Requires-Dist: pip-tools ; extra == 'dev'
Requires-Dist: pytest ; extra == 'dev'
